nekobin/__init__.py
nekobin/client.py
nekobin/errors.py
nekobin/types.py
nekobin/utils.py
nekobin-0.0.3.dist-info/LICENSE
nekobin-0.0.3.dist-info/METADATA
nekobin-0.0.3.dist-info/WHEEL
nekobin-0.0.3.dist-info/top_level.txt
nekobin-0.0.3.dist-info/RECORD
