Metadata-Version: 2.1
Name: nekobin
Version: 0.0.3
Summary: Nekobin API Wrapper
Home-page: https://github.com/OpenRestfulAPI/nekobinpy
Author: Pokurt
Author-email: poki@pokurt.me
License: GNU Lesser General Public License v3 (LGPLv3)
Platform: UNKNOWN
Classifier: Development Status :: 3 - Alpha
Classifier: Programming Language :: Python :: 3.8
Requires-Python: >=3.6
Requires-Dist: aiohttp (==3.7.4)
Requires-Dist: asyncio (==3.4.3)
